AUTHORS
HISTORY.rst
LICENSE
MANIFEST.in
README.md
setup.cfg
setup.py
pointdns/__init__.py
pointdns/api.py
pointdns/base.py
pointdns/exceptions.py
pointdns/helpers.py
pointdns.egg-info/PKG-INFO
pointdns.egg-info/SOURCES.txt
pointdns.egg-info/dependency_links.txt
pointdns.egg-info/requires.txt
pointdns.egg-info/top_level.txt