Metadata-Version: 1.1
Name: pointdns
Version: 0.1.2
Summary: pointhq.com API client with support for Python 3.x (based on pointhq package)
Home-page: https://github.com/cognetoapps/python-pointdns
Author: Cogneto.io
Author-email: accounts@copper.io
License: ISC
Download-URL: https://github.com/cognetoapps/python-pointdns/tarball/0.1.1
Platform: UNKNOWN
Classifier: Development Status :: 4 - Beta
Classifier: Intended Audience :: Developers
Classifier: License :: OSI Approved :: ISC License (ISCL)
Classifier: Programming Language :: Python
Classifier: Programming Language :: Python :: 2.6
Classifier: Programming Language :: Python :: 2.7
Classifier: Programming Language :: Python :: 3.0
Classifier: Programming Language :: Python :: 3.1
Classifier: Programming Language :: Python :: 3.2
Classifier: Programming Language :: Python :: 3.3
Classifier: Programming Language :: Python :: 3.4
Classifier: Topic :: Internet :: WWW/HTTP
